Metadata-Version: 2.1
Name: hifi-gan
Version: 0.0.2
Summary: Package up hifi-gan
Home-page: https://github.com/zachwe/hifi_gan
Author: Zach Wener-Fligner
Author-email: zbwener@gmail.com
License: MIT
Keywords: speech synthesis machine learning
Platform: UNKNOWN
Classifier: Development Status :: 3 - Alpha
Classifier: Topic :: Utilities
Classifier: License :: OSI Approved :: MIT License
